AUTHORS
INSTALL
LICENSE
MANIFEST.in
README.md
setup.py
django_rts.egg-info/PKG-INFO
django_rts.egg-info/SOURCES.txt
django_rts.egg-info/dependency_links.txt
django_rts.egg-info/pbr.json
django_rts.egg-info/top_level.txt
rts/__init__.py
rts/request_handlers.py
rts/response_generators.py
rts/serializers.py
rts/tests.py
rts/transformers.py
rts/views.py
rts/templates/rts/webform_autosubmit.html